pzip/__init__.py
pzip/__main__.py
pzip/base.py
pzip/cli.py
pzip/reader.py
pzip/writer.py
pzip-1.2.0.dist-info/METADATA
pzip-1.2.0.dist-info/WHEEL
pzip-1.2.0.dist-info/entry_points.txt
pzip-1.2.0.dist-info/licenses/LICENSE
pzip-1.2.0.dist-info/RECORD
