Metadata-Version: 2.3
Name: pzip
Version: 1.2.0
Summary: Crytographically secure file compression.
Project-URL: Homepage, https://github.com/imsweb/pzip
Author-email: Dan Watson <watsond@imsweb.com>
License: MIT
License-File: LICENSE
Classifier: Development Status :: 5 - Production/Stable
Classifier: Intended Audience :: Developers
Classifier: License :: OSI Approved :: MIT License
Classifier: Programming Language :: Python
Classifier: Programming Language :: Python :: 3
Classifier: Topic :: Security
Classifier: Topic :: System :: Archiving :: Compression
Requires-Python: >=3.8
Requires-Dist: cryptography
Provides-Extra: deflate
Requires-Dist: deflate; extra == 'deflate'
